Tarea 3/controlador_tester.v
/************************************************************
                    Universidad de Costa Rica
                 Escuela de Ingenieria Electrica
                            IE0523
                   Circuitos Digitales 2

                    controlador_tester.v

Autores: 
        Brenda Romero Solano <brenda.romero@ucr.ac.cr>

Fecha: 9/06/2024
   
*********************************************************** */



//! @title Pruebas del controlador
//! Este archivo contiene las pruebas del controlador. Se utilizan diferentes casos
//! de prueba para verificar el correcto funcionamiento del controlador en diferentes situaciones.

`timescale 1ns/1ns //Escala de timepo del reloj

module controlador_tester (
    output reg clk,              //! Esta es la salida del reloj
    output reg reset,            //! Esta es la salida del reset
    output reg [15:0] datain,    //! Esta es la salida de los datos de entrada
    output reg [1:0] slave_numb  //! Esta es la salida del número de esclavo
);

always #5 clk = !clk;

initial begin
    // Inicializando las señales
    reset = 1;
    clk = 1;
    datain = 0;
    slave_numb = 1;
    #10;
    reset = 0;
    // Prueba 01
    #10;
    datain = 16'hA569;

    #630;
    #10 slave_numb = 0;

    // Prueba 02
    #20 reset = 1;
    #30 reset = 0;
    datain = 16'h0AF0;
    slave_numb = 2;
    #640;
    #10 slave_numb = 0;
    #50 reset = 1;
    #40;
    $finish;
end

endmodule

Tarea 3/controlador.v
/************************************************************
                    Universidad de Costa Rica
                 Escuela de Ingenieria Electrica
                            IE0523
                   Circuitos Digitales 2

                    calculadora.v

Autores: 
        Brenda Romero Solano <brenda.romero@ucr.ac.cr>

Fecha: 9/6/2024 
    
*********************************************************** */ 


//! @title Master
//! Este módulo Verilog implementa un controlador maestro SPI que se comunica con dos esclavos.
//! El módulo utiliza una máquina de estados finitos (FSM) con tres estados para controlar la 
//! transmisión de datos SPI. En el estado inicial, espera a que se seleccione un esclavo.
//! Una vez seleccionado, comienza la transmisión de datos, ajustando las señales spi_cs y spi_sclk,
//! y gestionando los registros de datos mosi y miso. La FSM asegura que solo el esclavo seleccionado
//! esté activo, evitando conflictos en la línea MISO. Las señales de salida se asignan en función de
//! los registros internos y las entradas, permitiendo una comunicación SPI eficiente y sin conflictos.

module master (
    input clk,              //! Esta es la entrada del reloj
    input reset,            //! Esta es la entrada de reset
    input [15:0] datain,    //! Esta es la entrada de datos
    input [1:0]MISO,        //! Esta es la entrada de datos MISO
    input [1:0]slave_numb,  //! Esta es la entrada de selección de esclavo
    output CS_1,            //! Esta es la salida de selección del esclavo 1
    output CS_2,            //! Esta es la salida de selección del esclavo 2
    output SCLK,            //! Esta es la salida del reloj del SPI
    output [1:0]MOSI,       //! Esta es la salida de datos MOSI
    output [6:0] counter    //! Esta es la salida del contador
);

reg [15:0]  mosi;           //! Esta variable se encarga de almacenar los datos del master a un esclavo
reg [15:0]  miso;           //! Esta variable se encarga de almacenar los datos del esclavo al master
reg [2:0] state;            //! Esta variable representa el estado actual de la máquina de estados
reg [6:0] count;            //! Esta variable lleva la cuenta de los ciclos de reloj para la transmisión de datos
reg spi_cs;                 //! Esta variable controla la señal de selección del esclavo
reg spi_sclk;               //! Esta variable controla la señal de reloj del SPI

//! La lógica de cambio de estados
//! El módulo "master" tiene tres estados: estado 0, estado 1 y estado 2. En el estado 0, el módulo 
//! espera a que se seleccione un esclavo y configura las señales correspondientes. Luego, pasa al 
//! estado 1, donde comienza la transmisión de datos. En este estado, se ajustan las señales spi_cs 
//! y spi_sclk, y se gestionan los registros de datos mosi y miso. Finalmente, el módulo pasa al 
//! estado 2, donde se realiza la transición de reloj y se actualizan las señales según las 
//! condiciones establecidas. Si se cumple alguna de estas condiciones, el módulo vuelve al estado 0 
//! y reinicia las señales y registros correspondientes.

always @(posedge clk) begin
    if(reset) begin
        state <= 0;
        mosi <= 16'b0;
        miso <= 16'b0;
        count <=6'd32;
        spi_cs <= 1'b1;
        spi_sclk <= 1'b0;

    end else begin

        case (state)
            0 : begin
                mosi <= 16'b0;
                miso <= 16'b0;
                count <= 6'd32;
                spi_cs <= 1'b1;
                spi_sclk <= 1'b0;
                if(slave_numb != 0) begin
                    state <= 1;
                end
            end 
            1 :  begin
                spi_cs <= 0;
                spi_sclk <= 0;
                if (count > 16) begin
                    mosi <= datain[count-17];
                end else if (count <= 16) begin
                    miso[count-1] <= MISO;
                    mosi <= 0;
                end
                count <= count - 1;
                state <= 2;
            end
            2 : begin
                spi_sclk <= 1;
                if(count == 0) begin
                    state <= 0;
                    mosi <= 16'b0;
                    miso <= 16'b0;
                    count <= 6'd33;
                    spi_cs <= 1'b1;
                    spi_sclk <= 1'b0;
                end else if (count == 16) begin 
                    mosi <= 0;
                    state <= 1;
                end else if(count != 16) begin
                    state <= 1;
                end
            end
            default: state <= 0;
        endcase
    end
end

assign MOSI = mosi;                             //! Se actualiza la salida con los datos de la variable interna
assign counter = count;                         //! Se asigna el valor del contador interno a la salida
assign CS_1 = slave_numb == 1 ? spi_cs : 1;     //! Se asigna la señal de selección del esclavo 1 si el número de esclavo es 1, de lo contrario se asigna 1
assign CS_2 = slave_numb == 2 ? spi_cs : 1;     //! Se asigna la señal de selección del esclavo 2 si el número de esclavo es 2, de lo contrario se asigna 1
assign SCLK = spi_sclk;                         //! Se asigna la señal de reloj del SPI a la salida


endmodule

//! @title Slave
//! Este módulo Verilog implementa un esclavo SPI que se comunica con el controlador maestro.
//! El módulo utiliza una máquina de estados finitos (FSM) con tres estados para controlar la 
//! transmisión de datos SPI. En el estado inicial, el esclavo espera a que el controlador maestro
//! lo seleccione y configura las señales correspondientes. Luego, en el estado 1, el esclavo 
//! recibe los datos del controlador maestro y los almacena en el registro mosi. En el estado 2,
//! el esclavo transmite los datos almacenados en el registro mosi al controlador maestro a través
//! de la señal MISO. La FSM asegura que solo el esclavo seleccionado esté activo, evitando 
//! conflictos en la línea MISO.

module slave (
    input reset,            //! Esta es la entrada de reset
    output [1:0]MISO,       //! Esta es la salida de datos MISO
    input cs,               //! Esta es la entrada de selección del esclavo
    input SCLK,             //! Esta es la entrada del reloj del SPI
    input [6:0]counter,     //! Esta es la entrada del contador
    input [1:0]MOSI         //! Esta es la entrada de datos MOSI
);

reg [15:0]  mosi;           //! Esta variable se encarga de almacenar los datos del esclavo al master
reg [15:0]  miso;           //! Esta variable se encarga de almacenar los datos del master a un esclavo
reg [2:0] state;            //! Esta variable representa el estado actual de la máquina de estados

always @( posedge reset) begin
    miso <= 16'b0;
    state <= 0;
    mosi <= 0;
end

//! La lógica de cambio de estados
//! El módulo "slave" tiene tres estados: estado 0, estado 1 y estado 2. En el estado 0, el esclavo 
//! espera a que el controlador maestro lo seleccione y configura las señales correspondientes. Luego, 
//! en el estado 1, el esclavo recibe los datos del controlador maestro y los almacena en el registro 
//! mosi. En el estado 2, el esclavo transmite los datos almacenados en el registro mosi al controlador 
//! maestro a través de la señal MISO. La FSM asegura que solo el esclavo seleccionado esté activo, 
//! evitando conflictos en la línea MISO.

always @(posedge SCLK) begin
    case (state)
        0 : begin
            miso <= 16'b0;
            mosi <= 16'b0;
            if (~cs) begin
                state <= 1;
                mosi[15] <= MOSI;
            end
        end 
        1: begin
            if (counter > 16) begin
                mosi[counter-16] <= MOSI;
            end else begin 
                mosi[0] <= MOSI;
                state <= 2;
                miso <= mosi[15];
            end
        end
        2 :  begin
            if(counter == 0) begin
                miso <= mosi[0];
                mosi <= 16'b0;
                state <= 0;
            end  else  if (counter == 33) begin
                miso <=  16'b0;
            end else begin
                miso <= mosi[counter-1];
            end
        end
        default: state <= 0;
    endcase
end

assign MISO = state == 2 ? miso: 0;    

endmodule

//! @title Controlador
//! Este módulo Verilog implementa un controlador que utiliza el módulo maestro y dos módulos esclavos
//! para realizar la comunicación SPI. El controlador recibe datos de entrada y un número de esclavo
//! para seleccionar el esclavo correspondiente. Luego, el controlador utiliza el módulo maestro para
//! transmitir los datos al esclavo seleccionado y recibir los datos del esclavo. Los datos recibidos
//! se combinan y se envían como salida.

module controlador (
    input clk,              //! Esta es la entrada del reloj
    input reset,            //! Esta es la entrada de reset
    input [15:0] datain,    //! Esta es la entrada de datos
    input [1:0]slave_numb   //! Esta es la entrada de selección de esclavo
);
   wire SCLK,CS_1,CS_2;
   wire [1:0]MISO_1,MISO_2,MOSI;
   wire [6:0] counter;

   //! Instancia del master
    master master (
     .clk(clk),
     .reset(reset),
     .datain(datain),
     .CS_1(CS_1),
     .CS_2(CS_2),
     .SCLK(SCLK),
     .MOSI(MOSI),
     .counter(counter),
     .slave_numb(slave_numb),
     .MISO({1'b0,MISO_1||MISO_2})
     );
    //! Instancia del primer slave
     slave slave_1 (
     .reset(reset),
     .MISO(MISO_1),
     .cs(CS_1),
     .SCLK(SCLK),
     .counter(counter),
     .MOSI(MOSI)
     );
    //! Instancia del segundo slave
     slave slave_2 (
     .reset(reset),
     .MISO(MISO_2),
     .cs(CS_2),
     .SCLK(SCLK),
     .counter(counter),
     .MOSI(MOSI)
     );
endmodule

Tarea 3/testbench.v
/************************************************************
                    Universidad de Costa Rica
                 Escuela de Ingenieria Electrica
                            IE0523
                   Circuitos Digitales 2

                    testbench.v

Autores: 
        Brenda Romero Solano <brenda.romero@ucr.ac.cr>

Fecha: 9/06/2024

Descripcion: 
   
*********************************************************** */

`include "controlador.v"
`include "controlador_tester.v"

/* @title Testbench del controlador

Este módulo se encarga de crear una instancia tanto del controlador,
como de las pruebas creadas para la verifi-
cación del correcto funcionamiento del misma.
En caso de que no se compile correctamente, revisar que la dirección
desde donde se incluye el archivo sea la correcta, es decir, 
que la carpeta desde donde se abre la terminal sea la misma donde
están los archivos.*/ 
module testbench;
    wire clk, reset;
    wire [15:0] datain;
    wire [1:0]slave_numb;

controlador dut (
    .clk(clk),
    .reset(reset),
    .datain(datain),
    .slave_numb(slave_numb)
);

controlador_tester tester (
    .clk(clk),
    .reset(reset),
    .datain(datain),
    .slave_numb(slave_numb)
);
initial begin
    $dumpfile("testbench.vcd");
    $dumpvars;
end
endmodule

Tarea 3/testbench.vcd
$date
	Sun Jun 09 21:06:22 2024
$end
$version
	Icarus Verilog
$end
$timescale
	1ns
$end
$scope module testbench $end
$var wire 2 ! slave_numb [1:0] $end
$var wire 1 " reset $end
$var wire 16 # datain [15:0] $end
$var wire 1 $ clk $end
$scope module dut $end
$var wire 2 % slave_numb [1:0] $end
$var wire 1 " reset $end
$var wire 16 & datain [15:0] $end
$var wire 7 ' counter [6:0] $end
$var wire 1 $ clk $end
$var wire 1 ( SCLK $end
$var wire 2 ) MOSI [1:0] $end
$var wire 2 * MISO_2 [1:0] $end
$var wire 2 + MISO_1 [1:0] $end
$var wire 1 , CS_2 $end
$var wire 1 - CS_1 $end
$scope module master $end
$var wire 2 . MISO [1:0] $end
$var wire 1 ( SCLK $end
$var wire 7 / counter [6:0] $end
$var wire 2 0 slave_numb [1:0] $end
$var wire 1 " reset $end
$var wire 16 1 datain [15:0] $end
$var wire 1 $ clk $end
$var wire 2 2 MOSI [1:0] $end
$var wire 1 , CS_2 $end
$var wire 1 - CS_1 $end
$var reg 7 3 count [6:0] $end
$var reg 16 4 miso [15:0] $end
$var reg 16 5 mosi [15:0] $end
$var reg 1 6 spi_cs $end
$var reg 1 7 spi_sclk $end
$var reg 3 8 state [2:0] $end
$upscope $end
$scope module slave_1 $end
$var wire 2 9 MOSI [1:0] $end
$var wire 1 ( SCLK $end
$var wire 7 : counter [6:0] $end
$var wire 1 - cs $end
$var wire 1 " reset $end
$var wire 2 ; MISO [1:0] $end
$var reg 16 < miso [15:0] $end
$var reg 16 = mosi [15:0] $end
$var reg 3 > state [2:0] $end
$upscope $end
$scope module slave_2 $end
$var wire 2 ? MOSI [1:0] $end
$var wire 1 ( SCLK $end
$var wire 7 @ counter [6:0] $end
$var wire 1 , cs $end
$var wire 1 " reset $end
$var wire 2 A MISO [1:0] $end
$var reg 16 B miso [15:0] $end
$var reg 16 C mosi [15:0] $end
$var reg 3 D state [2:0] $end
$upscope $end
$upscope $end
$scope module tester $end
$var reg 1 $ clk $end
$var reg 16 E datain [15:0] $end
$var reg 1 " reset $end
$var reg 2 F slave_numb [1:0] $end
$upscope $end
$upscope $end
$enddefinitions $end
$comment Show the parameter values. $end
$dumpall
$end
#0
$dumpvars
b1 F
b0 E
b0 D
b0 C
b0 B
b0 A
b100000 @
b0 ?
b0 >
b0 =
b0 <
b0 ;
b100000 :
b0 9
b0 8
07
16
b0 5
b0 4
b100000 3
b0 2
b0 1
b1 0
b100000 /
b0 .
1-
1,
b0 +
b0 *
b0 )
0(
b100000 '
b0 &
b1 %
1$
b0 #
1"
b1 !
$end
#5
0$
#10
b1 8
1$
0"
#15
0$
#20
0-
b1 )
b1 2
b1 9
b1 ?
b10 8
b11111 '
b11111 /
b11111 :
b11111 @
b11111 3
b1 5
06
1$
b1010010101101001 #
b1010010101101001 &
b1010010101101001 1
b1010010101101001 E
#25
0$
#30
b1000000000000000 =
b1 >
b1 8
1(
17
1$
#35
0$
#40
b0 )
b0 2
b0 9
b0 ?
b10 8
b11110 '
b11110 /
b11110 :
b11110 @
b11110 3
b0 5
0(
07
1$
#45
0$
#50
b1 8
1(
17
1$
#55
0$
#60
b1 )
b1 2
b1 9
b1 ?
b10 8
b11101 '
b11101 /
b11101 :
b11101 @
b11101 3
b1 5
0(
07
1$
#65
0$
#70
b1010000000000000 =
b1 8
1(
17
1$
#75
0$
#80
b0 )
b0 2
b0 9
b0 ?
b10 8
b11100 '
b11100 /
b11100 :
b11100 @
b11100 3
b0 5
0(
07
1$
#85
0$
#90
b1 8
1(
17
1$
#95
0$
#100
b10 8
b11011 '
b11011 /
b11011 :
b11011 @
b11011 3
0(
07
1$
#105
0$
#110
b1 8
1(
17
1$
#115
0$
#120
b1 )
b1 2
b1 9
b1 ?
b10 8
b11010 '
b11010 /
b11010 :
b11010 @
b11010 3
b1 5
0(
07
1$
#125
0$
#130
b1010010000000000 =
b1 8
1(
17
1$
#135
0$
#140
b0 )
b0 2
b0 9
b0 ?
b10 8
b11001 '
b11001 /
b11001 :
b11001 @
b11001 3
b0 5
0(
07
1$
#145
0$
#150
b1 8
1(
17
1$
#155
0$
#160
b1 )
b1 2
b1 9
b1 ?
b10 8
b11000 '
b11000 /
b11000 :
b11000 @
b11000 3
b1 5
0(
07
1$
#165
0$
#170
b1010010100000000 =
b1 8
1(
17
1$
#175
0$
#180
b0 )
b0 2
b0 9
b0 ?
b10 8
b10111 '
b10111 /
b10111 :
b10111 @
b10111 3
b0 5
0(
07
1$
#185
0$
#190
b1 8
1(
17
1$
#195
0$
#200
b1 )
b1 2
b1 9
b1 ?
b10 8
b10110 '
b10110 /
b10110 :
b10110 @
b10110 3
b1 5
0(
07
1$
#205
0$
#210
b1010010101000000 =
b1 8
1(
17
1$
#215
0$
#220
b10 8
b10101 '
b10101 /
b10101 :
b10101 @
b10101 3
0(
07
1$
#225
0$
#230
b1010010101100000 =
b1 8
1(
17
1$
#235
0$
#240
b0 )
b0 2
b0 9
b0 ?
b10 8
b10100 '
b10100 /
b10100 :
b10100 @
b10100 3
b0 5
0(
07
1$
#245
0$
#250
b1 8
1(
17
1$
#255
0$
#260
b1 )
b1 2
b1 9
b1 ?
b10 8
b10011 '
b10011 /
b10011 :
b10011 @
b10011 3
b1 5
0(
07
1$
#265
0$
#270
b1010010101101000 =
b1 8
1(
17
1$
#275
0$
#280
b0 )
b0 2
b0 9
b0 ?
b10 8
b10010 '
b10010 /
b10010 :
b10010 @
b10010 3
b0 5
0(
07
1$
#285
0$
#290
b1 8
1(
17
1$
#295
0$
#300
b10 8
b10001 '
b10001 /
b10001 :
b10001 @
b10001 3
0(
07
1$
#305
0$
#310
b1 8
1(
17
1$
#315
0$
#320
b1 )
b1 2
b1 9
b1 ?
b10 8
b10000 '
b10000 /
b10000 :
b10000 @
b10000 3
b1 5
0(
07
1$
#325
0$
#330
b1 .
b1 +
b1 ;
b1 <
b10 >
b1010010101101001 =
b0 )
b0 2
b0 9
b0 ?
b1 8
b0 5
1(
17
1$
#335
0$
#340
b10 8
b1111 '
b1111 /
b1111 :
b1111 @
b1111 3
b1000000000000000 4
0(
07
1$
#345
0$
#350
b0 .
b0 +
b0 ;
b0 <
b1 8
1(
17
1$
#355
0$
#360
b10 8
b1110 '
b1110 /
b1110 :
b1110 @
b1110 3
0(
07
1$
#365
0$
#370
b1 .
b1 +
b1 ;
b1 <
b1 8
1(
17
1$
#375
0$
#380
b10 8
b1101 '
b1101 /
b1101 :
b1101 @
b1101 3
b1010000000000000 4
0(
07
1$
#385
0$
#390
b0 .
b0 +
b0 ;
b0 <
b1 8
1(
17
1$
#395
0$
#400
b10 8
b1100 '
b1100 /
b1100 :
b1100 @
b1100 3
0(
07
1$
#405
0$
#410
b1 8
1(
17
1$
#415
0$
#420
b10 8
b1011 '
b1011 /
b1011 :
b1011 @
b1011 3
0(
07
1$
#425
0$
#430
b1 .
b1 +
b1 ;
b1 <
b1 8
1(
17
1$
#435
0$
#440
b10 8
b1010 '
b1010 /
b1010 :
b1010 @
b1010 3
b1010010000000000 4
0(
07
1$
#445
0$
#450
b0 .
b0 +
b0 ;
b0 <
b1 8
1(
17
1$
#455
0$
#460
b10 8
b1001 '
b1001 /
b1001 :
b1001 @
b1001 3
0(
07
1$
#465
0$
#470
b1 .
b1 +
b1 ;
b1 <
b1 8
1(
17
1$
#475
0$
#480
b10 8
b1000 '
b1000 /
b1000 :
b1000 @
b1000 3
b1010010100000000 4
0(
07
1$
#485
0$
#490
b0 .
b0 +
b0 ;
b0 <
b1 8
1(
17
1$
#495
0$
#500
b10 8
b111 '
b111 /
b111 :
b111 @
b111 3
0(
07
1$
#505
0$
#510
b1 .
b1 +
b1 ;
b1 <
b1 8
1(
17
1$
#515
0$
#520
b10 8
b110 '
b110 /
b110 :
b110 @
b110 3
b1010010101000000 4
0(
07
1$
#525
0$
#530
b1 8
1(
17
1$
#535
0$
#540
b10 8
b101 '
b101 /
b101 :
b101 @
b101 3
b1010010101100000 4
0(
07
1$
#545
0$
#550
b0 .
b0 +
b0 ;
b0 <
b1 8
1(
17
1$
#555
0$
#560
b10 8
b100 '
b100 /
b100 :
b100 @
b100 3
0(
07
1$
#565
0$
#570
b1 .
b1 +
b1 ;
b1 <
b1 8
1(
17
1$
#575
0$
#580
b10 8
b11 '
b11 /
b11 :
b11 @
b11 3
b1010010101101000 4
0(
07
1$
#585
0$
#590
b0 .
b0 +
b0 ;
b0 <
b1 8
1(
17
1$
#595
0$
#600
b10 8
b10 '
b10 /
b10 :
b10 @
b10 3
0(
07
1$
#605
0$
#610
b1 8
1(
17
1$
#615
0$
#620
b10 8
b1 '
b1 /
b1 :
b1 @
b1 3
0(
07
1$
#625
0$
#630
b1 .
b1 +
b1 ;
b1 <
b1 8
1(
17
1$
#635
0$
#640
b10 8
b0 '
b0 /
b0 :
b0 @
b0 3
b1010010101101001 4
0(
07
1$
#645
0$
#650
b0 .
b0 +
b0 ;
b0 <
1-
16
b100001 '
b100001 /
b100001 :
b100001 @
b100001 3
b0 4
b0 8
0(
07
1$
#655
0$
#660
b100000 '
b100000 /
b100000 :
b100000 @
b100000 3
1$
b0 !
b0 %
b0 0
b0 F
#665
0$
#670
1$
#675
0$
#680
b0 =
b0 >
1$
1"
#685
0$
#690
1$
#695
0$
#700
1$
#705
0$
#710
b1 8
1$
b10 !
b10 %
b10 0
b10 F
b101011110000 #
b101011110000 &
b101011110000 1
b101011110000 E
0"
#715
0$
#720
0,
b10 8
b11111 '
b11111 /
b11111 :
b11111 @
b11111 3
06
1$
#725
0$
#730
b1 D
b1 8
1(
17
1$
#735
0$
#740
b10 8
b11110 '
b11110 /
b11110 :
b11110 @
b11110 3
0(
07
1$
#745
0$
#750
b1 8
1(
17
1$
#755
0$
#760
b10 8
b11101 '
b11101 /
b11101 :
b11101 @
b11101 3
0(
07
1$
#765
0$
#770
b1 8
1(
17
1$
#775
0$
#780
b10 8
b11100 '
b11100 /
b11100 :
b11100 @
b11100 3
0(
07
1$
#785
0$
#790
b1 8
1(
17
1$
#795
0$
#800
b1 )
b1 2
b1 9
b1 ?
b10 8
b11011 '
b11011 /
b11011 :
b11011 @
b11011 3
b1 5
0(
07
1$
#805
0$
#810
b100000000000 C
b1 8
1(
17
1$
#815
0$
#820
b0 )
b0 2
b0 9
b0 ?
b10 8
b11010 '
b11010 /
b11010 :
b11010 @
b11010 3
b0 5
0(
07
1$
#825
0$
#830
b1 8
1(
17
1$
#835
0$
#840
b1 )
b1 2
b1 9
b1 ?
b10 8
b11001 '
b11001 /
b11001 :
b11001 @
b11001 3
b1 5
0(
07
1$
#845
0$
#850
b101000000000 C
b1 8
1(
17
1$
#855
0$
#860
b0 )
b0 2
b0 9
b0 ?
b10 8
b11000 '
b11000 /
b11000 :
b11000 @
b11000 3
b0 5
0(
07
1$
#865
0$
#870
b1 8
1(
17
1$
#875
0$
#880
b1 )
b1 2
b1 9
b1 ?
b10 8
b10111 '
b10111 /
b10111 :
b10111 @
b10111 3
b1 5
0(
07
1$
#885
0$
#890
b101010000000 C
b1 8
1(
17
1$
#895
0$
#900
b10 8
b10110 '
b10110 /
b10110 :
b10110 @
b10110 3
0(
07
1$
#905
0$
#910
b101011000000 C
b1 8
1(
17
1$
#915
0$
#920
b10 8
b10101 '
b10101 /
b10101 :
b10101 @
b10101 3
0(
07
1$
#925
0$
#930
b101011100000 C
b1 8
1(
17
1$
#935
0$
#940
b10 8
b10100 '
b10100 /
b10100 :
b10100 @
b10100 3
0(
07
1$
#945
0$
#950
b101011110000 C
b1 8
1(
17
1$
#955
0$
#960
b0 )
b0 2
b0 9
b0 ?
b10 8
b10011 '
b10011 /
b10011 :
b10011 @
b10011 3
b0 5
0(
07
1$
#965
0$
#970
b1 8
1(
17
1$
#975
0$
#980
b10 8
b10010 '
b10010 /
b10010 :
b10010 @
b10010 3
0(
07
1$
#985
0$
#990
b1 8
1(
17
1$
#995
0$
#1000
b10 8
b10001 '
b10001 /
b10001 :
b10001 @
b10001 3
0(
07
1$
#1005
0$
#1010
b1 8
1(
17
1$
#1015
0$
#1020
b10 8
b10000 '
b10000 /
b10000 :
b10000 @
b10000 3
0(
07
1$
#1025
0$
#1030
b10 D
b1 8
1(
17
1$
#1035
0$
#1040
b10 8
b1111 '
b1111 /
b1111 :
b1111 @
b1111 3
0(
07
1$
#1045
0$
#1050
b1 8
1(
17
1$
#1055
0$
#1060
b10 8
b1110 '
b1110 /
b1110 :
b1110 @
b1110 3
0(
07
1$
#1065
0$
#1070
b1 8
1(
17
1$
#1075
0$
#1080
b10 8
b1101 '
b1101 /
b1101 :
b1101 @
b1101 3
0(
07
1$
#1085
0$
#1090
b1 8
1(
17
1$
#1095
0$
#1100
b10 8
b1100 '
b1100 /
b1100 :
b1100 @
b1100 3
0(
07
1$
#1105
0$
#1110
b1 .
b1 *
b1 A
b1 B
b1 8
1(
17
1$
#1115
0$
#1120
b10 8
b1011 '
b1011 /
b1011 :
b1011 @
b1011 3
b100000000000 4
0(
07
1$
#1125
0$
#1130
b0 .
b0 *
b0 A
b0 B
b1 8
1(
17
1$
#1135
0$
#1140
b10 8
b1010 '
b1010 /
b1010 :
b1010 @
b1010 3
0(
07
1$
#1145
0$
#1150
b1 .
b1 *
b1 A
b1 B
b1 8
1(
17
1$
#1155
0$
#1160
b10 8
b1001 '
b1001 /
b1001 :
b1001 @
b1001 3
b101000000000 4
0(
07
1$
#1165
0$
#1170
b0 .
b0 *
b0 A
b0 B
b1 8
1(
17
1$
#1175
0$
#1180
b10 8
b1000 '
b1000 /
b1000 :
b1000 @
b1000 3
0(
07
1$
#1185
0$
#1190
b1 .
b1 *
b1 A
b1 B
b1 8
1(
17
1$
#1195
0$
#1200
b10 8
b111 '
b111 /
b111 :
b111 @
b111 3
b101010000000 4
0(
07
1$
#1205
0$
#1210
b1 8
1(
17
1$
#1215
0$
#1220
b10 8
b110 '
b110 /
b110 :
b110 @
b110 3
b101011000000 4
0(
07
1$
#1225
0$
#1230
b1 8
1(
17
1$
#1235
0$
#1240
b10 8
b101 '
b101 /
b101 :
b101 @
b101 3
b101011100000 4
0(
07
1$
#1245
0$
#1250
b1 8
1(
17
1$
#1255
0$
#1260
b10 8
b100 '
b100 /
b100 :
b100 @
b100 3
b101011110000 4
0(
07
1$
#1265
0$
#1270
b0 .
b0 *
b0 A
b0 B
b1 8
1(
17
1$
#1275
0$
#1280
b10 8
b11 '
b11 /
b11 :
b11 @
b11 3
0(
07
1$
#1285
0$
#1290
b1 8
1(
17
1$
#1295
0$
#1300
b10 8
b10 '
b10 /
b10 :
b10 @
b10 3
0(
07
1$
#1305
0$
#1310
b1 8
1(
17
1$
#1315
0$
#1320
b10 8
b1 '
b1 /
b1 :
b1 @
b1 3
0(
07
1$
#1325
0$
#1330
b1 8
1(
17
1$
#1335
0$
#1340
b10 8
b0 '
b0 /
b0 :
b0 @
b0 3
0(
07
1$
#1345
0$
#1350
1,
16
b100001 '
b100001 /
b100001 :
b100001 @
b100001 3
b0 4
b0 8
0(
07
1$
#1355
0$
#1360
b100000 '
b100000 /
b100000 :
b100000 @
b100000 3
1$
b0 !
b0 %
b0 0
b0 F
#1365
0$
#1370
1$
#1375
0$
#1380
1$
#1385
0$
#1390
1$
#1395
0$
#1400
1$
#1405
0$
#1410
b0 C
b0 D
1$
1"
