Proyecto Digitales 1/Sist_Seguridad_Tests.v
/************************************************************
                    Universidad de Costa Rica
                 Escuela de Ingenieria Electrica
                            IE0323
                   Circuitos Digitales 1

                    Sist_Seguridad_Tests.v

Autores: 
        Brenda Romero Solano <brenda.romero@ucr.ac.cr>
        Alejandra Solano Ramírez <mariaalejandra.solano@ucr.ac.cr>
        Jun Hyun Yeom Song <jun.yeom@ucr.ac.cr>

Fecha: 27/02/2024

Descripcion: 
    Contiene el módulo donde se describen las pruebas necesarias para
confirmar que la máquina de de estados funciona correctamente.

Nota: Si utiliza la extensión TerosHDL y presiona desde el menú
desplegado el icono de libro, podrá tener una mejor vista de la 
documentación.
*********************************************************** */

//! @title Pruebas del sistema de seguridad
//! En este modulo se encuentran las diferentes pruebas que confirmarán
//! el correcto funcionamiento de la máquina descrita en el archivo
//! Sist_Seguiridad.v, de modo que se guarden en el archivo Sist_Seguridad.vcd.
//!
//! Dependiendo del entorno donde se ejecute este programa, dicho archivo
//! puede guardarse en la misma carpeta que contiene este archivo, o una
//! carpeta build.
module Sist_Seguridad_Tests (
    output reg clk, //! Esta es la salida del reloj
    output reg rst, //! Esta es la salida del reset
    output reg ho, //! Esta es la salida del detector de humo
    output reg pw, //! Esta es la salida de la contraseña
    output reg ro, //! Esta es la salida del cronómetro
    output reg vo, //! Esta es la salida de la ventana cero
    output reg v1, //! Esta es la salida de la ventana uno
    output reg mo, //! Esta es la salida del sensor de movimiento cero
    output reg m1, //! Esta es la salida del sensor de movimiento uno
    output reg po, //! Esta es la salida de la puerta cero
    output reg p1, //! Esta es la salida de la puerta uno
    input wire io, //! Esta es la entrada de la alarma de incendios
    input wire lo, //! Esta es la entrada de las luces de advertencia
    input wire ao  //! Esta es la entrada de la alarma de robos
);
    //! Creación de la señal del reloj para el análisis del sistema
	initial clk=0; 

	always #1 begin
        clk = ~clk;
    end 
    initial begin
        $dumpfile("Sist_Seguridad.vcd");
        $dumpvars;

    // Pruebas para el Sistema

	// Prueba 1 - Comienza desarmado y se arma correctamente
        rst=1;
        #1 rst = 0;
        #2 ho = 0;
        #2 pw = 1;
        #2 ro = 1;
        #2;
        pw = 0;
        ro = 0; //Apagado de señales para no interferir las demás pruebas
    
    // Prueba 2 - Comienza desarmado y hay una ventana abierta
        #4 rst = 1;
        #1 rst = 0;
        v1 = 1;
        #2 v1 = 0; //Apagado de señales para no interferir las demás pruebas

    // Prueba 3 - Comienza armado y se desarma correctamente
        #4 rst = 1;
        #1 rst=0;
        ho = 0; //Estado Armado
        pw = 1;
        ro = 1;
        #4 rst = 1; // Dado que no hay caminos para pasar directamente del estado a al b, se hace un reset
        #1 rst = 0;
        pw = 0; //Apagado de señales para no interferir las demas pruebas
        ro = 0;

    // Prueba 4 - Comienza armado y se abre una ventana
        #4 rst = 1;
        #1 rst = 0;
        ho = 0; //Estado Armado
        pw = 1;
        ro = 1;
        #4 vo = 1;
        pw = 0; //Se apagan las señales para que no detecte la contraseña
        ro = 0;
        #2 vo = 0;//Apagado de señales para no interferir las demas pruebas

    // Prueba 5 - Comienza armado y se abre una puerta, el usuario ingresa la contraseña correcta
        #4 rst = 1;
        #1 rst = 0;
        ho = 0; //Estado Armado
        pw = 1;
        ro = 1;
        #4 po = 1;
        ro = 0; //Se apaga la señal para que no detecte el estado armado
        #2 po = 0;  //Apagado de señales para no interferir las demas pruebas

    // Prueba 6 - Comienza armado y el empleado ingresa la contraseña incorrecta dos veces
        #4 rst = 1;
        #1 rst = 0;
        ho = 0; //Estado Armado
        pw = 1;
        ro = 1;
        #4 p1 = 1;
        ro = 0; 
        pw = 0;
        #2 p1 = 0; //Apagado de señales para no interferir las demás pruebas

    // Prueba 7 - Comienza armado y se activa la alarma contra incendios
        #4 rst = 1;
        #1 rst = 0;
        ho = 0; //Estado armado
        pw = 1;
        ro = 1;
        #4 ho = 1;
        ro = 0;
        pw = 0;
        #2 ho = 0; //Apagado de señales para no interferir las demás pruebas

    // Prueba 8 - Comienza desarmado y se activa la alarma contra incendios
        #4 rst = 1;
        #1 rst = 0;
        #2 ho = 1;
        #2 ho = 0; //Apagado de señales para no interferir las demás pruebas
        
    // Prueba 9 - Comienza armado, se detecta movimiento y se ingresa la contraseña correcta
        #4 rst = 1;
        #1 rst = 0;
        ho = 0; //Estado armado
        pw = 1;
        ro = 1;
        #2 ro = 0; //Apagado de señales para no detectar el estado armado
        pw = 0;
        #4 mo = 1;
        #4 pw = 1;
        #2 mo =0;
        pw =0; //Apagado de señales para no interferir las demás pruebas

        
    // Prueba 10 - Comienza en estado de incendio y se ingresa la contraseña correcta
        #4 rst = 1;
        #1 rst = 0;
        ho = 1; //Estado incendio
        #4 pw = 1;
        ho = 0;
        #2 ro = 0; //Apagado de señales para no interferir las demás pruebas
        pw =0;

        #10 $finish;
    end

endmodule

Proyecto Digitales 1/Sist_Seguridad.v
/************************************************************
                    Universidad de Costa Rica
                 Escuela de Ingenieria Electrica
                            IE0323
                   Circuitos Digitales 1

                    Sist_Seguridad.v

Autores: 
        Brenda Romero Solano <brenda.romero@ucr.ac.cr>
        Alejandra Solano Ramírez <mariaalejandra.solano@ucr.ac.cr>
        Jun Hyun Yeom Song <jun.yeom@ucr.ac.cr>

Fecha: 27/02/2024

Descripción: 
    Contiene el módulo de un sistema de seguridad de
una empresa que utiliza los distintos sensores para proteger
a la misma de situaciones peligrosas.

Nota: Si utiliza la extensión TerosHDL y presiona desde el menú
desplegado el icono de libro, podrá tener una mejor vista de la 
documentación.
*********************************************************** */


//! @title Sistema de seguridad
//! Este módulo se encarga de controlar la activación de las luces de seguridad
//! dependiendo del estado en el que se encuentre la máquina, de modo que si se detecta alguna
//! situación peligrosa, se pueda identificar de manera correcta para poder resolver la situación
//! satisfactoriamente. 
module Sist_Seguridad (
    input wire clk, //! Esta es la entrada del reloj
    input wire rst, //! Esta es la entrada del reset
    input wire ho, //! Esta es la entrada del detector de humo
    input wire pw, //! Esta es la entrada de la contraseña
    input wire ro, //! Esta es la entrada del cronómetro
    input wire vo, //! Esta es la entrada de la ventana cero
    input wire v1, //! Esta es la entrada de la ventana uno
    input wire mo, //! Esta es la entrada del sensor de movimiento cero
    input wire m1, //! Esta es la entrada del sensor de movimiento uno
    input wire po, //! Esta es la entrada de la puerta cero
    input wire p1, //! Esta es la entrada de la puerta uno
    output reg io, //! Esta es la salida de la alarma de incendios
    output reg lo, //! Esta es la salida de las luces de advertencia
    output reg ao  //! Esta es la salida de la alarma de robos
    );
    
    reg[2:0] estado_actual; //! Esta variable mostrará el estado actual de la máquina
    reg[2:0] estado_futuro; //! Esta variable mostrará el estado futuro de la máquina

    // Asignación de estados
    parameter a = 3'b000; //!Estado Desarmado
    parameter b = 3'b111; //!Estado Armado
    parameter c = 3'b010; //!Estado Robo
    parameter d = 3'b011; //!Estado de Entrada Autorizada
    parameter e = 3'b100; //!Estado de Entrada Autorizada con un Intento Fallido
    parameter f = 3'b001; //!Estado de Incendio

    //! Memoria de estados de la máquina de estados, la cual se activa en cada ciclo
    //! positivo del reloj o del ciclo positivo del reset

    always @(posedge clk, posedge rst) begin
        if (rst) estado_actual = a;
        else estado_actual <= estado_futuro;  
    end

    //! Lógica de cálculo próximo estado de la máquina de estados
    always @(*) begin
        case (estado_actual)

            /* En esta sección se muestran las distintas formas
            de pasar a otros estados desde el estado a*/
            a:begin
                if (ho) estado_futuro = f;
                else if(pw & ro) estado_futuro = b;
                else estado_futuro = a;
            end

            /* En esta sección se muestran las distintas formas
            de pasar a otros estados desde el estado b*/
            b:begin
                if (vo|v1|mo|m1) estado_futuro = c;
                else if (po|p1) estado_futuro = d;
                else if (ho) estado_futuro = f;
                else estado_futuro = b;
            end

            /* En esta sección se muestran las distintas formas
            de pasar a otros estados desde el estado c*/
            c:begin
                if (pw) begin
                    estado_futuro = a;
                end else begin
                    estado_futuro = c; 
                end 
            end

            /* En esta sección se muestran las distintas formas
            de pasar a otros estados desde el estado d*/
            d:begin
                case ({ro,pw})
                    2'b00: estado_futuro = e;
                    2'b01: estado_futuro = a;
                    2'b10: estado_futuro = c;
                    2'b11: estado_futuro = c;
                endcase
            end

            /* En esta sección se muestran las distintas formas
            de pasar a otros estados desde el estado e*/
            e:begin
                if (pw) begin
                    estado_futuro = a;
                end else begin
                    estado_futuro = c; 
                end
            end

            /* En esta sección se muestran las distintas formas
            de pasar a otros estados desde el estado f*/
            f:begin
                if (pw) begin
                    estado_futuro = a;
                end else begin
                    estado_futuro = f; 
                end
            end

        endcase
        
    //! Lógica de cambio de las salidas la cual indica cuando se encienden las salidas
        io = (estado_actual == f) ? 1: 0;
        lo = ((estado_actual == c) | (estado_actual == d)| ( estado_actual == e) | (estado_actual == f )) ? 1:0;
        ao = (estado_actual == c) ? 1 : 0;    
    end
endmodule

Proyecto Digitales 1/Sist_Seguridad_tb.v
/************************************************************
                    Universidad de Costa Rica
                 Escuela de Ingenieria Electrica
                            IE0323
                   Circuitos Digitales 1

                    Sist_Seguridad_tb.v

Autores: 
        Brenda Romero Solano <brenda.romero@ucr.ac.cr>
        Alejandra Solano Ramírez <mariaalejandra.solano@ucr.ac.cr>
        Jun Hyun Yeom Song <jun.yeom@ucr.ac.cr>

Fecha: 27/02/2024

Descripcion: 
    Contiene el modulo que se encarga de realizar las pruebas 
con la máquina de estados creada del archivo Sist_Seguridad.v
con las pruebas del archivo Sist_Seguridad_Tests.v para
verificar que todo funciona correctamente.

Nota: Si utiliza la extensión TerosHDL y presiona desde el menú
desplegado el icono de libro, podrá tener una mejor vista de la 
documentación.
*********************************************************** */


`include "Sist_Seguridad.v"
`include "Sist_Seguridad_Tests.v"

/* @title Testbench del Sistema de seguridad

Este módulo se encarga de crear una instancia tanto de la
máquina de estados, como de las pruebas creadas para la verifi-
cación del correcto funcionamiento de la misma.
En caso de que no se compile correctamente, revisar que la dirección
desde donde se incluye el archivo sea la correcta, es decir, 
que la carpeta desde donde se abre la terminal sea la misma donde
están los archivos.*/ 
module Sist_Seguridad_tb();
    
    //!Entradas y salidas a utilizar
    wire clk,rst, ho,pw,ro,vo,v1,mo,m1,po,p1,io,lo,ao;

   //! Instancia de la máquina de estados
    Sist_Seguridad maquina (
        .clk(clk),
        .rst(rst), 
        .ho(ho),
        .pw(pw),
        .ro(ro),
        .vo(vo),
        .v1(v1),
        .mo(mo),
        .m1(m1),
        .po(po),
        .p1(p1),
        .io(io),
        .lo(lo),
        .ao(ao)
    );
    //! Instancia de las pruebas realizadas
    Sist_Seguridad_Tests patitos_s_a (
        .clk(clk),
        .rst(rst), 
        .ho(ho),
        .pw(pw),
        .ro(ro),
        .vo(vo),
        .v1(v1),
        .mo(mo),
        .m1(m1),
        .po(po),
        .p1(p1),
        .io(io),
        .lo(lo),
        .ao(ao)
    );
endmodule

Proyecto Digitales 1/Sist_Seguridad.vcd
$date
	Tue Feb 27 19:03:15 2024
$end
$version
	Icarus Verilog
$end
$timescale
	1s
$end
$scope module Sist_Seguridad_tb $end
$var wire 1 ! vo $end
$var wire 1 " v1 $end
$var wire 1 # rst $end
$var wire 1 $ ro $end
$var wire 1 % pw $end
$var wire 1 & po $end
$var wire 1 ' p1 $end
$var wire 1 ( mo $end
$var wire 1 ) m1 $end
$var wire 1 * lo $end
$var wire 1 + io $end
$var wire 1 , ho $end
$var wire 1 - clk $end
$var wire 1 . ao $end
$scope module maquina $end
$var wire 1 ! vo $end
$var wire 1 " v1 $end
$var wire 1 # rst $end
$var wire 1 $ ro $end
$var wire 1 % pw $end
$var wire 1 & po $end
$var wire 1 ' p1 $end
$var wire 1 ( mo $end
$var wire 1 ) m1 $end
$var wire 1 , ho $end
$var wire 1 - clk $end
$var parameter 3 / a $end
$var parameter 3 0 b $end
$var parameter 3 1 c $end
$var parameter 3 2 d $end
$var parameter 3 3 e $end
$var parameter 3 4 f $end
$var reg 1 . ao $end
$var reg 3 5 estado_actual [2:0] $end
$var reg 3 6 estado_futuro [2:0] $end
$var reg 1 + io $end
$var reg 1 * lo $end
$upscope $end
$scope module patitos_s_a $end
$var wire 1 . ao $end
$var wire 1 + io $end
$var wire 1 * lo $end
$var reg 1 - clk $end
$var reg 1 , ho $end
$var reg 1 ) m1 $end
$var reg 1 ( mo $end
$var reg 1 ' p1 $end
$var reg 1 & po $end
$var reg 1 % pw $end
$var reg 1 $ ro $end
$var reg 1 # rst $end
$var reg 1 " v1 $end
$var reg 1 ! vo $end
$upscope $end
$upscope $end
$enddefinitions $end
$comment Show the parameter values. $end
$dumpall
b1 4
b100 3
b11 2
b10 1
b111 0
b0 /
$end
#0
$dumpvars
b0 6
b0 5
0.
0-
x,
0+
0*
x)
x(
x'
x&
x%
x$
1#
x"
x!
$end
#1
0#
1-
#2
0-
#3
1-
0,
#4
0-
#5
1-
1%
#6
0-
#7
b111 5
b111 6
1-
1$
#8
0-
#9
1-
0$
0%
#10
0-
#11
1-
#12
0-
#13
b0 6
b0 5
1-
1#
#14
0-
1"
0#
#15
1-
#16
0-
0"
#17
1-
#18
0-
#19
1-
#20
0-
1#
#21
b111 5
b111 6
1-
1$
1%
0#
#22
0-
#23
1-
#24
0-
#25
b0 5
1-
1#
#26
b0 6
0-
0$
0%
0#
#27
1-
#28
0-
#29
1-
#30
0-
1#
#31
b111 5
b111 6
1-
1$
1%
0#
#32
0-
#33
1-
#34
0-
#35
1.
1*
b10 5
b10 6
1-
0$
0%
1!
#36
0-
#37
1-
0!
#38
0-
#39
1-
#40
0-
#41
0.
0*
b0 6
b0 5
1-
1#
#42
b111 6
0-
1$
1%
0#
#43
b111 5
1-
#44
0-
#45
1-
#46
b11 6
0-
0$
1&
#47
1*
b0 6
b11 5
1-
#48
0-
0&
#49
0*
b0 5
1-
#50
0-
#51
1-
#52
0-
1#
#53
b111 5
b111 6
1-
1$
0#
#54
0-
#55
1-
#56
0-
#57
1*
b11 5
b100 6
1-
0%
0$
1'
#58
0-
#59
b10 6
b100 5
1-
0'
#60
0-
#61
1.
b10 5
1-
#62
0-
#63
0.
0*
b0 6
b0 5
1-
1#
#64
b111 6
0-
1$
1%
0#
#65
b111 5
1-
#66
0-
#67
1-
#68
b1 6
0-
0%
0$
1,
#69
1*
1+
b1 5
1-
#70
0-
0,
#71
1-
#72
0-
#73
1-
#74
0*
0+
b0 6
b0 5
0-
1#
#75
1-
0#
#76
0-
#77
1*
1+
b1 5
b1 6
1-
1,
#78
0-
#79
1-
0,
#80
0-
#81
1-
#82
0-
#83
0*
0+
b0 6
b0 5
1-
1#
#84
b111 6
0-
1$
1%
0#
#85
b111 5
1-
#86
0-
0%
0$
#87
1-
#88
0-
#89
1-
#90
b10 6
0-
1(
#91
1.
1*
b10 5
1-
#92
0-
#93
1-
#94
b0 6
0-
1%
#95
0.
0*
b0 5
1-
#96
0-
0%
0(
#97
1-
#98
0-
#99
1-
#100
0-
1#
#101
1*
1+
b1 5
b1 6
1-
1,
0#
#102
0-
#103
1-
#104
0-
#105
0*
0+
b0 5
b0 6
1-
0,
1%
#106
0-
#107
1-
0%
