Proyecto Digitales 1/Teclado_Tests.v
/************************************************************
                    Universidad de Costa Rica
                 Escuela de Ingenieria Electrica
                            IE0323
                   Circuitos Digitales 1

                    Sist_Seguridad_Tests.v

Autores: 
        Brenda Romero Solano <brenda.romero@ucr.ac.cr>
        Alejandra Solano Ramírez <mariaalejandra.solano@ucr.ac.cr>
        Jun Hyun Yeom Song <jun.yeom@ucr.ac.cr>

Fecha: 27/02/2024

Descripcion: 
    Contiene el modulo donde se describen las pruebas necesarias para
confirmar que el teclado funciona correctamente.

Nota: Si utiliza la extensión TerosHDL y presiona desde el menú
desplegado el icono de libro, podrá tener una mejor vista de la 
documentación.
*********************************************************** */

//! @title Pruebas del Teclado
//! En este modulo se encuentran las diferentes pruebas que confirmarán
//! el correcto funcionamiento del teclado descrito en el archivo Teclado.v, 
//! de modo que se guarden en el archivo Teclado.vcd.
//!
//! Dependiendo del entorno donde se ejecute este programa, dicho archivo
//! puede guardarse en la misma carpeta que contiene este archivo, o una
//! carpeta build.
module Teclado_Test(
    output reg clk,           //! Señal de reloj
    output reg rst,           //! Señal de reset
    output reg [9:0] teclas,  //! Señal de teclas
    output reg enter,         //! Señal de tecla enter
    input wire verificacion   //! Señal de verificación de contraseña
);
    //! Creación de la señal del reloj para el análisis del sistema
	initial clk=0; 

	always #1 begin
        clk = ~clk;
    end 

    initial begin
        $dumpfile("Teclado.vcd");
        $dumpvars;

        // Inicializa las señales de entrada
        teclas = 10'b0000000000;
        enter = 0;

    // Pruebas para el teclado
        
    // Prueba 1: Ingresa la contraseña correctamente
        #4 rst=1;
        #1 rst=0;
        teclas[4] = 1;    // Se presiona la tecla 4
        #2 teclas[4] = 0; // Se deja de precionar la tecla
        #2 teclas[3] = 1; // Se presiona la tecla 3
        #2 teclas[3] = 0; // Se deja de presionar la tecla
        #2 teclas[2] = 1; // Se presiona la tecla 2
        #2 teclas[2] = 0; // Se deja de presionar la tecla
        #2 teclas[1] = 1; // Se presiona la tecla 1
        #2 teclas[1] = 0; // Se deja de presionar la tecla
        #4 enter = 1;     // Presiona la tecla enter
        #4 enter = 0;     //Apagado de las señales para no interferir las demás pruebas

    // Prueba 2: Ingresa una contraseña incorrecta
        #4 rst=1;
        #1 rst=0;
        #1 teclas[7] = 1; // Se presiona la tecla 7
        #2 teclas[7] = 0; // Se deja de presionar la tecla
        #2 teclas[2] = 1; // Se presiona la tecla 2
        #2 teclas[2] = 0; // Se deja de presionar la tecla
        #2 teclas[3] = 1; // Se presiona la tecla 3
        #2 teclas[3] = 0; // Se deja de presionar la tecla
        #2 teclas[1] = 1; // Se presiona la tecla 1
        #2 teclas[1] = 0; // Se deja de presionar la tecla
        #4 enter = 1;     // Presiona la tecla enter
        #4 enter = 0;     //Apagado de las señales para no interferir las demás pruebas

        // Se ingresa la contraseña correcta
        #4 teclas[4] = 1; // Se presiona la tecla 4
        #2 teclas[4] = 0; // Se deja de presionar la tecla
        #2 teclas[3] = 1; // Se presiona la tecla 3
        #2 teclas[3] = 0; // Se deja de presionar la tecla
        #2 teclas[2] = 1; // Se presiona la tecla 2
        #2 teclas[2] = 0; // Se deja de presionar la tecla
        #2 teclas[1] = 1; // Se presiona la tecla 1
        #2 teclas[1] = 0; // Se deja de presionar la tecla
        #4 enter = 1;     // Presiona la tecla enter
        #4 enter = 0;     // Apagado de las señales para no interferir las demás pruebas


    // Prueba 3: Se ingresan dos contraseñas incorrectas
        #4 rst=1;
        #1 rst=0;
        #1 teclas[7] = 1; // Se presiona la tecla 7
        #2 teclas[7] = 0; // Se deja de presionar la tecla
        #2 teclas[2] = 1; // Se presiona la tecla 2
        #2 teclas[2] = 0; // Se deja de presionar la tecla
        #2 teclas[3] = 1; // Se presiona la tecla 3
        #2 teclas[3] = 0; // Se deja de presionar la tecla
        #2 teclas[1] = 1; // Se presiona la tecla 1
        #2 teclas[1] = 0; // Se deja de presionar la tecla
        #2 teclas[2] = 1; // Se presiona la tecla 2
        #2 teclas[2] = 0; // Se deja de presionar la tecla
        #4 enter = 1;     // Presiona la tecla enter
        #4 enter = 0;     //Apagado de las señales para no interferir las demás pruebas
        
        // Se ingresa la contraseña incorrecta
        #4 teclas[2] = 1; // Se presiona la tecla 4
        #2 teclas[2] = 0; // Se deja de presionar la tecla
        #2 teclas[2] = 1; // Se presiona la tecla 3
        #2 teclas[2] = 0; // Se deja de presionar la tecla
        #2 teclas[2] = 1; // Se presiona la tecla 2
        #2 teclas[2] = 0; // Se deja de presionar la tecla
        #2 teclas[2] = 1; // Se presiona la tecla 1
        #2 teclas[2] = 0; // Se deja de presionar la tecla
        #4 enter = 1;     // Presiona la tecla enter
        #4 enter = 0;     // Apagado de las señales para no interferir las demás pruebas 
       
        // Finaliza la simulación
        #10 $finish;
    end

endmodule

Proyecto Digitales 1/Teclado.v
/************************************************************
                    Universidad de Costa Rica
                 Escuela de Ingenieria Electrica
                            IE0323
                   Circuitos Digitales 1

                    Teclado.v

Autores: 
        Brenda Romero Solano <brenda.romero@ucr.ac.cr>
        Alejandra Solano Ramírez <mariaalejandra.solano@ucr.ac.cr>
        Jun Hyun Yeom Song <jun.yeom@ucr.ac.cr>

Fecha: 27/02/2024

Descripcion: 
    Contiene el módulo de un teclado que revisa si la contraseña ingresada
mediante una interfaz que tiene 10 teclas numéricas y una de enter. Dado que la contraseña
se encuentra en formato BCD, se convierte la señal de la tecla presionada a este formato, para
que cuando se presione la tecla enter, se comparen las entradas recibidas y la clave almacenada
en el sistema con el fin de averiguar si es la correcta o no.

Nota: Si utiliza la extensión TerosHDL y presiona desde el menú
desplegado el icono de libro, podrá tener una mejor vista de la 
documentación.
*********************************************************** */


//! @title Teclado
//!  Este módulo se encarga de recibir una contraseña desde un teclado con 10 teclas numerales
//! diferentes y una de Enter, el cual espera a que se active la tecla Enter para analizar
//! la contraseña ingresada por el usuario y compararla por la que tiene con el sistema
//! para finalmente devolver un uno si estas son iguales o un cero si son diferentes,
//! en caso de que se ingresen más de cuatro números, el sistema considerará que la misma es incorrecta
//! y restablecerá el valor de la contraseña actual de modo que la salida sea 0.
//! Además, el modulo también se encarga de convertir el valor de la tecla en un número en 
//! formato BCD. 
module Teclado(
    input wire clk,          //! Esta es la entrada del reloj
    input wire rst,          //! Esta es la entrada del reset
    input wire [9:0] teclas, //! Estas son las entradas  de las teclas
    input wire enter,        //! Esta es la entrada de la tecla Enter
    output reg verificacion  //! Esta es la salida que indica si la contraseña es correcta
    );


reg [15:0] clave_temporal;   //! Esta variable tendrá el valor temporal de la contraseña mientras se escribe
reg [15:0] clave_convertida; //! Esta variable tendrá la contraseña codificada en BCD
reg [3:0]  contador;         //! Esta variable se utiliza para saber cuántas teclas se han tocado
reg estado_actual;           //! Esta variable mostrará el estado actual de la máquina
reg estado_futuro;           //! Esta variable mostrará el estado futuro de la máquina

parameter  CLAVE = 16'b0100001100100001 ; //! Contraseña del sistema: 4321
parameter a = 1'b1;                       //!Estado ingresando contraseña
parameter b = 1'b0;                       //!Estado confirmando contraseña


//! Memoria de estados de la máquina de estados, la cual se activa en cada ciclo
//! positivo del reloj o del ciclo positivo del reset
always @(posedge clk, posedge rst) begin
    if (rst) begin
        estado_actual = a; //! Se reinician los valores utilizados anteriormente
        estado_futuro = a;      
        assign verificacion = 0;
        clave_temporal = 16'h0000; 
        clave_convertida = 16'h0000;
        contador = 0;
    end else estado_actual <= estado_futuro;  
end

//! Lógica de cálculo próximo estado de la máquina de estado
always @(posedge clk, posedge rst) begin
    if(estado_actual)begin
        if (enter) begin  //! Se revisa si se ha tocado la tecla Enter
            clave_convertida = clave_temporal; //! Carga la contraseña ya convertida
            contador = 0;
            estado_actual = b;
            estado_futuro = b;

        end else begin

            //Actualización de la contraseña temporal
            if (|teclas) begin

                case (contador)

                //Caso cuando se detecta una tecla activada
                0:begin
                    if (teclas[0]) clave_temporal <= {clave_temporal[3:0],4'b0000};
                    else if (teclas[1]) clave_temporal <= {clave_temporal[3:0],4'b0001};
                    else if (teclas[2]) clave_temporal <= {clave_temporal[3:0],4'b0010};
                    else if (teclas[3]) clave_temporal <= {clave_temporal[3:0],4'b0011};
                    else if (teclas[4]) clave_temporal <= {clave_temporal[3:0],4'b0100};
                    else if (teclas[5]) clave_temporal <= {clave_temporal[3:0],4'b0101};
                    else if (teclas[6]) clave_temporal <= {clave_temporal[3:0],4'b0110};
                    else if (teclas[7]) clave_temporal <= {clave_temporal[3:0],4'b0111};
                    else if (teclas[8]) clave_temporal <= {clave_temporal[3:0],4'b1000};
                    else if (teclas[9]) clave_temporal <= {clave_temporal[3:0],4'b1001};
                end
                //Caso cuando se detectan dos teclas activadas
                1: begin
                    if (teclas[0]) clave_temporal <= {clave_temporal[7:0],4'b0000};
                    else if (teclas[1]) clave_temporal <= {clave_temporal[7:0],4'b0001};
                    else if (teclas[2]) clave_temporal <= {clave_temporal[7:0],4'b0010};
                    else if (teclas[3]) clave_temporal <= {clave_temporal[7:0],4'b0011};
                    else if (teclas[4]) clave_temporal <= {clave_temporal[7:0],4'b0100};
                    else if (teclas[5]) clave_temporal <= {clave_temporal[7:0],4'b0101};
                    else if (teclas[6]) clave_temporal <= {clave_temporal[7:0],4'b0110};
                    else if (teclas[7]) clave_temporal <= {clave_temporal[7:0],4'b0111};
                    else if (teclas[8]) clave_temporal <= {clave_temporal[7:0],4'b1000};
                    else if (teclas[9]) clave_temporal <= {clave_temporal[7:0],4'b1001};
                end
                //Caso cuando se detectan tres teclas activadas
                2: begin
                    if (teclas[0]) clave_temporal <= {clave_temporal[11:0],4'b0000};
                    else if (teclas[1]) clave_temporal <= {clave_temporal[11:0],4'b0001};
                    else if (teclas[2]) clave_temporal <= {clave_temporal[11:0],4'b0010};
                    else if (teclas[3]) clave_temporal <= {clave_temporal[11:0],4'b0011};
                    else if (teclas[4]) clave_temporal <= {clave_temporal[11:0],4'b0100};
                    else if (teclas[5]) clave_temporal <= {clave_temporal[11:0],4'b0101};
                    else if (teclas[6]) clave_temporal <= {clave_temporal[11:0],4'b0110};
                    else if (teclas[7]) clave_temporal <= {clave_temporal[11:0],4'b0111};
                    else if (teclas[8]) clave_temporal <= {clave_temporal[11:0],4'b1000};
                    else if (teclas[9]) clave_temporal <= {clave_temporal[11:0],4'b1001};
                end
                //Caso cuando se detectan cuatro teclas activadas
                3: begin
                    if (teclas[0]) clave_temporal <= {clave_temporal[15:0],4'b0000};
                    else if (teclas[1]) clave_temporal <= {clave_temporal[15:0],4'b0001};
                    else if (teclas[2]) clave_temporal <= {clave_temporal[15:0],4'b0010};
                    else if (teclas[3]) clave_temporal <= {clave_temporal[15:0],4'b0011};
                    else if (teclas[4]) clave_temporal <= {clave_temporal[15:0],4'b0100};
                    else if (teclas[5]) clave_temporal <= {clave_temporal[15:0],4'b0101};
                    else if (teclas[6]) clave_temporal <= {clave_temporal[15:0],4'b0110};
                    else if (teclas[7]) clave_temporal <= {clave_temporal[15:0],4'b0111};
                    else if (teclas[8]) clave_temporal <= {clave_temporal[15:0],4'b1000};
                    else if (teclas[9]) clave_temporal <= {clave_temporal[15:0],4'b1001};
                end

                /* En caso de que se ingresen más números de los requeridos, se reiniciará
                la clave para que en el momento de la verificación, se muestre que la contraseña
                es inncorrecta*/ 
                default: clave_temporal <= 16'h0000;

                endcase

                contador <= contador + 1;
            end       
        end
    end else begin

        //! Verificación  de contraseña
        if (clave_convertida !== CLAVE)begin
            clave_temporal = 16'h0000; //! Se reinician los valores utilizados anteriormente
            clave_convertida = 16'h0000;
            estado_futuro = a;
        end
    end

    //!Lógica de cambio de las salidas
    verificacion = (clave_convertida == CLAVE) ? 1 : 0 ;
end

endmodule

Proyecto Digitales 1/Teclado_tb.v
/************************************************************
                    Universidad de Costa Rica
                 Escuela de Ingenieria Electrica
                            IE0323
                   Circuitos Digitales 1

                    Teclado_tb.v

Autores: 
        Brenda Romero Solano <brenda.romero@ucr.ac.cr>
        Alejandra Solano Ramírez <mariaalejandra.solano@ucr.ac.cr>
        Jun Hyun Yeom Song <jun.yeom@ucr.ac.cr>

Fecha: 27/02/2024

Descripción: 
    Contiene el módulo que se encarga de realizar las pruebas 
con el teclado creado del archivo Teclado.v con las pruebas del
archivo Teclado_Tests.v para verificar que todo funciona correctamente.

Nota: Si utiliza la extensión TerosHDL y presiona desde el menú
desplegado el icono de libro, podrá tener una mejor vista de la 
documentación.
*********************************************************** */


`include "Teclado.v"
`include "Teclado_Tests.v"

/* @title Testbench del Teclado

Este módulo se encarga de crear una instancia tanto del teclado,
como de las pruebas creadas para la verificación del correcto
funcionamiento del mismo.
En caso de que no se compile correctamente, revisar que la dirección
desde donde se incluye el archivo sea la correcta, es decir, 
que la carpeta desde donde se abre la terminal sea la misma donde
están los archivos.*/ 
module Teclado_tb();
    
    //!Entradas y salidas a utilizar
    wire clk,rst;
    wire [9:0] teclas;
    wire enter, verificacion;

   //! Instancia del teclado
    Teclado teclado (
        .clk(clk),
        .rst(rst), 
        .teclas(teclas),
        .enter(enter),
        .verificacion(verificacion)
    );
    //! Instancia de las pruebas realizadas
    Teclado_Test prueba (
        .clk(clk),
        .rst(rst), 
        .teclas(teclas),
        .enter(enter),
        .verificacion(verificacion)
    );
endmodule

Proyecto Digitales 1/Teclado.vcd
$date
	Tue Feb 27 19:02:54 2024
$end
$version
	Icarus Verilog
$end
$timescale
	1s
$end
$scope module Teclado_tb $end
$var wire 1 ! verificacion $end
$var wire 10 " teclas [9:0] $end
$var wire 1 # rst $end
$var wire 1 $ enter $end
$var wire 1 % clk $end
$scope module prueba $end
$var wire 1 ! verificacion $end
$var reg 1 % clk $end
$var reg 1 $ enter $end
$var reg 1 # rst $end
$var reg 10 & teclas [9:0] $end
$upscope $end
$scope module teclado $end
$var wire 1 % clk $end
$var wire 1 $ enter $end
$var wire 1 # rst $end
$var wire 10 ' teclas [9:0] $end
$var parameter 16 ( CLAVE $end
$var parameter 1 ) a $end
$var parameter 1 * b $end
$var reg 16 + clave_convertida [15:0] $end
$var reg 16 , clave_temporal [15:0] $end
$var reg 4 - contador [3:0] $end
$var reg 1 . estado_actual $end
$var reg 1 / estado_futuro $end
$var reg 1 ! verificacion $end
$upscope $end
$upscope $end
$enddefinitions $end
$comment Show the parameter values. $end
$dumpall
0*
1)
b100001100100001 (
$end
#0
$dumpvars
x/
x.
bx -
bx ,
bx +
b0 '
b0 &
0%
0$
x#
b0 "
x!
$end
#1
1.
0!
1/
b0 +
b0 ,
1%
#2
0%
#3
1%
#4
b0 -
0%
1#
#5
b1 -
b100 ,
1%
b10000 "
b10000 &
b10000 '
0#
#6
0%
#7
1%
b0 "
b0 &
b0 '
#8
0%
#9
b10 -
b1000011 ,
1%
b1000 "
b1000 &
b1000 '
#10
0%
#11
1%
b0 "
b0 &
b0 '
#12
0%
#13
b11 -
b10000110010 ,
1%
b100 "
b100 &
b100 '
#14
0%
#15
1%
b0 "
b0 &
b0 '
#16
0%
#17
b100 -
b100001100100001 ,
1%
b10 "
b10 &
b10 '
#18
0%
#19
1%
b0 "
b0 &
b0 '
#20
0%
#21
1%
#22
0%
#23
0/
0.
b0 -
b100001100100001 +
1%
1$
#24
0%
#25
1%
#26
0%
#27
1%
0$
#28
0%
#29
1%
#30
0%
#31
b0 +
b0 ,
1/
1.
1%
1#
#32
0%
0#
#33
b1 -
b111 ,
1%
b10000000 "
b10000000 &
b10000000 '
#34
0%
#35
1%
b0 "
b0 &
b0 '
#36
0%
#37
b10 -
b1110010 ,
1%
b100 "
b100 &
b100 '
#38
0%
#39
1%
b0 "
b0 &
b0 '
#40
0%
#41
b11 -
b11100100011 ,
1%
b1000 "
b1000 &
b1000 '
#42
0%
#43
1%
b0 "
b0 &
b0 '
#44
0%
#45
b100 -
b111001000110001 ,
1%
b10 "
b10 &
b10 '
#46
0%
#47
1%
b0 "
b0 &
b0 '
#48
0%
#49
1%
#50
0%
#51
0/
0.
b0 -
b111001000110001 +
1%
1$
#52
0%
#53
1/
b0 +
b0 ,
1%
#54
0%
#55
1.
1%
0$
#56
0%
#57
1%
#58
0%
#59
b1 -
b100 ,
1%
b10000 "
b10000 &
b10000 '
#60
0%
#61
1%
b0 "
b0 &
b0 '
#62
0%
#63
b10 -
b1000011 ,
1%
b1000 "
b1000 &
b1000 '
#64
0%
#65
1%
b0 "
b0 &
b0 '
#66
0%
#67
b11 -
b10000110010 ,
1%
b100 "
b100 &
b100 '
#68
0%
#69
1%
b0 "
b0 &
b0 '
#70
0%
#71
b100 -
b100001100100001 ,
1%
b10 "
b10 &
b10 '
#72
0%
#73
1%
b0 "
b0 &
b0 '
#74
0%
#75
1%
#76
0%
#77
0/
1.
b0 -
b100001100100001 +
1%
1$
#78
0%
#79
0.
1%
#80
0%
#81
1%
0$
#82
0%
#83
1%
#84
0%
#85
b0 +
b0 ,
1/
1.
1%
1#
#86
0%
0#
#87
b1 -
b111 ,
1%
b10000000 "
b10000000 &
b10000000 '
#88
0%
#89
1%
b0 "
b0 &
b0 '
#90
0%
#91
b10 -
b1110010 ,
1%
b100 "
b100 &
b100 '
#92
0%
#93
1%
b0 "
b0 &
b0 '
#94
0%
#95
b11 -
b11100100011 ,
1%
b1000 "
b1000 &
b1000 '
#96
0%
#97
1%
b0 "
b0 &
b0 '
#98
0%
#99
b100 -
b111001000110001 ,
1%
b10 "
b10 &
b10 '
#100
0%
#101
1%
b0 "
b0 &
b0 '
#102
0%
#103
b101 -
b0 ,
1%
b100 "
b100 &
b100 '
#104
0%
#105
1%
b0 "
b0 &
b0 '
#106
0%
#107
1%
#108
0%
#109
0/
1.
b0 -
1%
1$
#110
0%
#111
0.
1%
#112
0%
#113
1/
1%
0$
#114
0%
#115
1.
1%
#116
0%
#117
b1 -
b10 ,
1%
b100 "
b100 &
b100 '
#118
0%
#119
1%
b0 "
b0 &
b0 '
#120
0%
#121
b10 -
b100010 ,
1%
b100 "
b100 &
b100 '
#122
0%
#123
1%
b0 "
b0 &
b0 '
#124
0%
#125
b11 -
b1000100010 ,
1%
b100 "
b100 &
b100 '
#126
0%
#127
1%
b0 "
b0 &
b0 '
#128
0%
#129
b100 -
b10001000100010 ,
1%
b100 "
b100 &
b100 '
#130
0%
#131
1%
b0 "
b0 &
b0 '
#132
0%
#133
1%
#134
0%
#135
0/
0.
b0 -
b10001000100010 +
1%
1$
#136
0%
#137
1/
b0 +
b0 ,
1%
#138
0%
#139
1.
1%
0$
