Laboratorio 1/calle_tester.v
/************************************************************
                    Universidad de Costa Rica
                 Escuela de Ingenieria Electrica
                            IE0523
                   Circuitos Digitales 2

                    calle_tester.v

Autores: 
        Brenda Romero Solano <brenda.romero@ucr.ac.cr>

Fecha: 2/04/2024

Descripcion: 
   
*********************************************************** */

//! @title Pruebas de la calle
//! Este módulo se encarga de realizar las pruebas correspondientes
//! para saber si los semáforos funcionan correctamente
//! Dependiendo del entorno donde se ejecute este programa, dicho archivo
//! puede guardarse en la misma carpeta que contiene este archivo, o una
//! carpeta build.
`timescale 1ns/1ns //Escala de timepo del reloj/ timeprecision

module calle_tester (
// Puertos
    output reg clk,                  //! Esta es la salida del reloj
    output reg enb,                  //! Esta es la salida de encendido
    output reg[1:0] semaforo_a,      //! Esta es la salida del semáforo A
    output reg reset,                //! Esta es la salida del reset
    output reg[1:0] semaforo_b,      //! Esta es la salida del semáforo B
    input wire a_peatonal,           //! Esta es la entrada del semáforo peatonal A
    input wire b_peatonal            //! Esta es la entrada del semáforo peatonal B
);

 //! Creación de la señal del reloj para el análisis del sistema
always begin
    #2 clk = !clk;    
end

initial begin
    clk = 0;
    reset = 1'b0;
    enb = 1;
    $display("Se ha ingresado al tester");

//! Prueba 1- Semáforo A en verde y semáforo B en rojo
    semaforo_a = 2'b10;
    semaforo_b = 2'b00;
    #10 semaforo_b = 2'b01;
//! Prueba 2- Semáforo A en verde y semáforo B en verde 
    #4 semaforo_b = 2'b10;

//! Prueba 3- Semáforo A en amarillo y semáforo B en verde 
    #12 semaforo_a = 2'b01;

//! Prueba 4- Semáforo A en rojo y semáforo B en verde
    #8 semaforo_a = 2'b00;
    #8 reset = 1;
    #4  reset = 0;

//! Prueba 5- Semáforo A en rojo y semáforo B en amarillo
    #8  semaforo_a = 2'b00;
    semaforo_b = 2'b01;
//! Prueba 6- Semáforo A en rojo y semáforo B en verde eneble en 0
    #8 semaforo_b = 2'b10;  
    enb=0;
    #8 enb=1;
    semaforo_a = 2'b01;
    #4 semaforo_b = 2'b01;

//! Prueba 7- Semáforo A en verde y semáforo B en rojo 
    #8 semaforo_a = 2'b10;
    semaforo_b = 2'b00;

    #10 $finish;

end
endmodule

Laboratorio 1/calle.v
/************************************************************
                    Universidad de Costa Rica
                 Escuela de Ingenieria Electrica
                            IE0523
                   Circuitos Digitales 2

                    calle.v

Autores: 
        Brenda Romero Solano <brenda.romero@ucr.ac.cr>

Fecha: 2/04/2024

Descripción: Este es el módulo que se encarga de controlar
los semáforos peatonales de una calle según los colores que tienen
los semáforos vehículares. 
    
*********************************************************** */


//! @title calle 
module calle (
// Puertos
    input wire clk,                  //! Esta es la entrada del reloj
    input wire enb,                  //! Esta es la entrada de encendido
    input wire[1:0] semaforo_a,      //! Esta es la entrada del semáforo A
    input wire reset,                //! Esta es la entrada del reset
    input wire[1:0] semaforo_b,      //! Esta es la entrada del semáforo B
    output reg a_peatonal,           //! Esta es la salida del semáforo peatonal A
    output reg b_peatonal            //! Esta es la salida del semáforo peatonal B
);   
// Parametros del módulo 
    parameter rojo = 2'b00;         //! Color rojo del semáforo
    parameter amarillo = 2'b01;     //! Color amarillo del semáforo
    parameter verde = 2'b10;        //! Color verde del semáforo

// Procesos del módulo
    //! Este proceso se encarga de revisar primeramente, si la 
    //! entrada eneble esta activa o no, y si el reset esta desactivado
    //! de modo que revise posteriormente las condiciones para que los
    //! semáforos se activen, donde en caso de que el semáforo a este en rojo
    //! y el b este en verde, se procederá a activar el semáforo peatonal a, en
    //! caso contrario, se encenderá el b, si ninguna de estas situaciones, sucede
    //! ambos semáforos se mantendrán apagados
    always @(posedge clk) begin 
        if (enb && ~reset) begin
            if(semaforo_a == rojo && semaforo_b == verde)begin
                a_peatonal <= 1;
                b_peatonal <= 0;
            end else if(semaforo_b == rojo && semaforo_a == verde)begin
                a_peatonal <= 0;
                b_peatonal <= 1;
            end else begin
                a_peatonal <= 0;
                b_peatonal <= 0;
            end
                                  
        end else if (reset) begin
            a_peatonal <= 0;
            b_peatonal <= 0;
        end
    end
    
endmodule

Laboratorio 1/calle_testbench.v
/************************************************************
                    Universidad de Costa Rica
                 Escuela de Ingenieria Electrica
                            IE0523
                   Circuitos Digitales 2

                    calle_testbench.v

Autores: 
        Brenda Romero Solano <brenda.romero@ucr.ac.cr>

Fecha: 2/04/2024

Descripcion: 
   
*********************************************************** */

`include "calle.v"
`include "calle_tester.v"

/* @title Testbench de la call

Este módulo se encarga de crear una instancia tanto de la
calle, como de las pruebas creadas para la verifi-
cación del correcto funcionamiento de la misma.
En caso de que no se compile correctamente, revisar que la dirección
desde donde se incluye el archivo sea la correcta, es decir, 
que la carpeta desde donde se abre la terminal sea la misma donde
están los archivos.*/ 
module calle_testbench;
    //!Entradas y salidas a utilizar
    wire clk, enb, reset,a_peatonal,b_peatonal;
    wire[1:0]semaforo_a,semaforo_b ;

//! Instancia de la calle
calle DUT(
    .clk(clk), 
    .enb(enb),
    .semaforo_a(semaforo_a),
    .reset(reset),
    .semaforo_b(semaforo_b), 
    .a_peatonal(a_peatonal), 
    .b_peatonal(b_peatonal)
);

//! Instancia de las pruebas realizadas
calle_tester tester(
    .clk(clk), 
    .enb(enb),
    .semaforo_a(semaforo_a),
    .reset(reset),
    .semaforo_b(semaforo_b), 
    .a_peatonal(a_peatonal), 
    .b_peatonal(b_peatonal)
);

/* Para generar las ondas y
y visualizar en gtkwave
*/
initial begin
    $dumpfile("calle_testbench.vcd");
    $dumpvars;
end

endmodule

Laboratorio 1/build/calle_testbench.vcd
$date
	Thu May 02 20:35:10 2024
$end
$version
	Icarus Verilog
$end
$timescale
	1ns
$end
$scope module calle_testbench $end
$var wire 2 ! semaforo_b [1:0] $end
$var wire 2 " semaforo_a [1:0] $end
$var wire 1 # reset $end
$var wire 1 $ enb $end
$var wire 1 % clk $end
$var wire 1 & b_peatonal $end
$var wire 1 ' a_peatonal $end
$scope module DUT $end
$var wire 2 ( semaforo_b [1:0] $end
$var wire 2 ) semaforo_a [1:0] $end
$var wire 1 # reset $end
$var wire 1 $ enb $end
$var wire 1 % clk $end
$var parameter 2 * amarillo $end
$var parameter 2 + rojo $end
$var parameter 2 , verde $end
$var reg 1 ' a_peatonal $end
$var reg 1 & b_peatonal $end
$upscope $end
$scope module tester $end
$var wire 1 ' a_peatonal $end
$var wire 1 & b_peatonal $end
$var reg 1 % clk $end
$var reg 1 $ enb $end
$var reg 1 # reset $end
$var reg 2 - semaforo_a [1:0] $end
$var reg 2 . semaforo_b [1:0] $end
$upscope $end
$upscope $end
$enddefinitions $end
$comment Show the parameter values. $end
$dumpall
b10 ,
b0 +
b1 *
$end
#0
$dumpvars
b0 .
b10 -
b10 )
b0 (
x'
x&
0%
1$
0#
b10 "
b0 !
$end
#2
1&
0'
1%
#4
0%
#6
1%
#8
0%
#10
0&
1%
b1 !
b1 (
b1 .
#12
0%
#14
1%
b10 !
b10 (
b10 .
#16
0%
#18
1%
#20
0%
#22
1%
#24
0%
#26
1%
b1 "
b1 )
b1 -
#28
0%
#30
1%
#32
0%
#34
1'
1%
b0 "
b0 )
b0 -
#36
0%
#38
1%
#40
0%
#42
0'
1%
1#
#44
0%
#46
1'
1%
0#
#48
0%
#50
1%
#52
0%
#54
0'
1%
b1 !
b1 (
b1 .
#56
0%
#58
1%
#60
0%
#62
1%
0$
b10 !
b10 (
b10 .
#64
0%
#66
1%
#68
0%
#70
1%
b1 "
b1 )
b1 -
1$
#72
0%
#74
1%
b1 !
b1 (
b1 .
#76
0%
#78
1%
#80
0%
#82
1&
1%
b0 !
b0 (
b0 .
b10 "
b10 )
b10 -
